{
  "signals": {
    "M30": {
      "summary_reco": "SELL",
      "summary_buy": 3,
      "summary_sell": 14,
      "summary_neutral": 9,
      "osc_reco": "NEUTRAL",
      "ma_reco": "STRONG_SELL",
      "close": 1.16185
    },
    "H1": {
      "summary_reco": "STRONG_SELL",
      "summary_buy": 1,
      "summary_sell": 16,
      "summary_neutral": 9,
      "osc_reco": "NEUTRAL",
      "ma_reco": "STRONG_SELL",
      "close": 1.16185
    }
  },
  "last_check_utc": "2026-05-18T05:15:19.934002+00:00"
}